iQModules/__init__.py
iQModules/classes.py
iQModules/methods.py
iQModules-1.0.0.dist-info/LICENSE
iQModules-1.0.0.dist-info/METADATA
iQModules-1.0.0.dist-info/WHEEL
iQModules-1.0.0.dist-info/top_level.txt
iQModules-1.0.0.dist-info/RECORD
